lewinb/__init__.py
lewinb/_modidx.py
lewinb/core.py
lewinb-0.0.1.dist-info/LICENSE
lewinb-0.0.1.dist-info/METADATA
lewinb-0.0.1.dist-info/WHEEL
lewinb-0.0.1.dist-info/entry_points.txt
lewinb-0.0.1.dist-info/top_level.txt
lewinb-0.0.1.dist-info/RECORD
